ascpy/__init__.py
ascpy/utils.py
ascpy-0.1.0.dist-info/METADATA
ascpy-0.1.0.dist-info/WHEEL
ascpy-0.1.0.dist-info/top_level.txt
ascpy-0.1.0.dist-info/RECORD
